jupyterlab_dmn/__init__.py
jupyterlab_dmn/_version.py
jupyterlab_dmn-0.2.0.data/data/share/jupyter/labextensions/jupyterlab-dmn/package.json
jupyterlab_dmn-0.2.0.data/data/share/jupyter/labextensions/jupyterlab-dmn/static/4bd3a7546d27598054171a664a0717d23d2cc1dcf34f0d2ce5f28d1f712aa7fa.svg
jupyterlab_dmn-0.2.0.data/data/share/jupyter/labextensions/jupyterlab-dmn/static/568.4064045308897c53faaa.js
jupyterlab_dmn-0.2.0.data/data/share/jupyter/labextensions/jupyterlab-dmn/static/747.fea355cadf766ac19a5b.js
jupyterlab_dmn-0.2.0.data/data/share/jupyter/labextensions/jupyterlab-dmn/static/798.da6c81a38d295b649ae5.js
jupyterlab_dmn-0.2.0.data/data/share/jupyter/labextensions/jupyterlab-dmn/static/798.da6c81a38d295b649ae5.js.LICENSE.txt
jupyterlab_dmn-0.2.0.data/data/share/jupyter/labextensions/jupyterlab-dmn/static/c1f0fd50668fccdd65d74a9ca6aa2fc34bd18a0682b825c846abb72f8ade26c3.eot
jupyterlab_dmn-0.2.0.data/data/share/jupyter/labextensions/jupyterlab-dmn/static/d643dc8a9e1edf4646162dd63d176590333a6e7de07a9671d22a05bcab8f44fd.ttf
jupyterlab_dmn-0.2.0.data/data/share/jupyter/labextensions/jupyterlab-dmn/static/remoteEntry.dbcc8768c61cb61d3eec.js
jupyterlab_dmn-0.2.0.data/data/share/jupyter/labextensions/jupyterlab-dmn/static/style.js
jupyterlab_dmn-0.2.0.data/data/share/jupyter/labextensions/jupyterlab-dmn/static/third-party-licenses.json
jupyterlab_dmn-0.2.0.data/data/share/jupyter/labextensions/jupyterlab-dmn/install.json
jupyterlab_dmn-0.2.0.dist-info/METADATA
jupyterlab_dmn-0.2.0.dist-info/WHEEL
jupyterlab_dmn-0.2.0.dist-info/licenses/LICENSE
jupyterlab_dmn-0.2.0.dist-info/RECORD
