Metadata-Version: 2.1
Name: jupyterlab-dmn
Version: 0.2.0
Summary: A JupyterLab extension for rendering DMN files
Project-URL: Homepage, https://github.com/datakurre/jupyterlab-dmn
Project-URL: Bug Tracker, https://github.com/datakurre/jupyterlab-dmn/issues
Project-URL: Repository, https://github.com/datakurre/jupyterlab-dmn.git
Author-email: Asko Soukka <asko.soukka@iki.fi>
License:                                  Apache License
License-File: LICENSE
Classifier: Framework :: Jupyter
Classifier: Framework :: Jupyter :: JupyterLab
Classifier: Framework :: Jupyter :: JupyterLab :: 3
Classifier: Framework :: Jupyter :: JupyterLab :: Extensions
Classifier: Framework :: Jupyter :: JupyterLab :: Extensions :: Prebuilt
Classifier: License :: OSI Approved :: Apache Software License
Classifier: Programming Language :: Python
Classifier: Programming Language :: Python :: 3
Classifier: Programming Language :: Python :: 3.7
Classifier: Programming Language :: Python :: 3.8
Classifier: Programming Language :: Python :: 3.9
Classifier: Programming Language :: Python :: 3.10
Classifier: Programming Language :: Python :: 3.11
Requires-Python: >=3.7
